<?xml version="1.0" encoding="utf-8" ?>
<dwsync>
<file name="jquery.ui.accordion.min.js" server="hud.mx//veritas.hud.mx/" local="129948025330221546" remote="129931438800000000" Dst="2" />
<file name="jquery.ui.autocomplete.min.js" server="hud.mx//veritas.hud.mx/" local="129948025336905991" remote="129931438800000000" Dst="2" />
<file name="jquery.ui.button.min.js" server="hud.mx//veritas.hud.mx/" local="129948025338577096" remote="129931438800000000" Dst="2" />
<file name="jquery.ui.core.min.js" server="hud.mx//veritas.hud.mx/" local="129948025338577096" remote="129931438800000000" Dst="2" />
<file name="jquery.ui.dialog.min.js" server="hud.mx//veritas.hud.mx/" local="129948025345321594" remote="129931438800000000" Dst="2" />
<file name="jquery.ui.datepicker.min.js" server="hud.mx//veritas.hud.mx/" local="129948025347022731" remote="129931438800000000" Dst="2" />
<file name="jquery.ui.draggable.min.js" server="hud.mx//veritas.hud.mx/" local="129948025347022731" remote="129931438800000000" Dst="2" />
<file name="jquery.ui.droppable.min.js" server="hud.mx//veritas.hud.mx/" local="129948025349484363" remote="129931438800000000" Dst="2" />
<file name="jquery.ui.mouse.min.js" server="hud.mx//veritas.hud.mx/" local="129948025353587156" remote="129931438800000000" Dst="2" />
<file name="jquery.ui.position.min.js" server="hud.mx//veritas.hud.mx/" local="129948025356008761" remote="129931438800000000" Dst="2" />
<file name="jquery.ui.progressbar.min.js" server="hud.mx//veritas.hud.mx/" local="129948025356849270" remote="129931438800000000" Dst="2" />
<file name="jquery.ui.resizable.min.js" server="hud.mx//veritas.hud.mx/" local="129948025363363605" remote="129931438800000000" Dst="2" />
<file name="jquery.ui.selectable.min.js" server="hud.mx//veritas.hud.mx/" local="129948025363363605" remote="129931438800000000" Dst="2" />
<file name="jquery.ui.slider.min.js" server="hud.mx//veritas.hud.mx/" local="129948025364194159" remote="129931438800000000" Dst="2" />
<file name="jquery.ui.tabs.min.js" server="hud.mx//veritas.hud.mx/" local="129948025371699163" remote="129931438800000000" Dst="2" />
<file name="jquery.ui.sortable.min.js" server="hud.mx//veritas.hud.mx/" local="129948025373300281" remote="129931438800000000" Dst="2" />
<file name="jquery.ui.widget.min.js" server="hud.mx//veritas.hud.mx/" local="129948025373310292" remote="129931438800000000" Dst="2" />
</dwsync>